README.md
setup.py
DAO_module.egg-info/PKG-INFO
DAO_module.egg-info/SOURCES.txt
DAO_module.egg-info/dependency_links.txt
DAO_module.egg-info/requires.txt
DAO_module.egg-info/top_level.txt
dao_module/DAO.py
dao_module/__init__.py