Metadata-Version: 1.2
Name: DAO-module
Version: 1.2
Summary: Модуль для работы с удаленной БД
Home-page: https://github.com/SADT-Boting/DAO-Module
Author: BuldakovN
Author-email: nikitabuldakov@mail.ru
License: UNKNOWN
Platform: UNKNOWN
Requires-Python: >=3.5
